widgetwizard/__init__.py
widgetwizard/config.json
widgetwizard/widgetwizard.py
widgetwizard-0.9.4.data/data/widgetwizard/config.json
widgetwizard-0.9.4.dist-info/LICENSE
widgetwizard-0.9.4.dist-info/METADATA
widgetwizard-0.9.4.dist-info/WHEEL
widgetwizard-0.9.4.dist-info/dependency_links.txt
widgetwizard-0.9.4.dist-info/top_level.txt
widgetwizard-0.9.4.dist-info/RECORD
