Metadata-Version: 2.1
Name: widgetwizard
Version: 0.9.4
Summary: Widget Wizard is a Python automation module that allows you to create widget and extension code base structures for your Oracle Commerce Cloud projects.
Home-page: https://github.com/valdal14/widgetwizard
Author: Valerio D'Alessio - @valdal14
Author-email: valerio.dalessio@oracle.com
License: MIT
Platform: UNKNOWN
Classifier: Programming Language :: Python :: 3
Classifier: License :: OSI Approved :: MIT License
Classifier: Operating System :: OS Independent
Requires-Python: >=3.7.1
Requires-Dist: requests
